sphinxcontrib_rextheme-0.1.2-py2.7-nspkg.pth
sphinxcontrib/rextheme.py
sphinxcontrib/rex/layout.html
sphinxcontrib/rex/theme.conf
sphinxcontrib/rex/static/rextheme.js
sphinxcontrib/rex/static/rextheme.css
sphinxcontrib_rextheme-0.1.2.dist-info/RECORD
sphinxcontrib_rextheme-0.1.2.dist-info/DESCRIPTION.rst
sphinxcontrib_rextheme-0.1.2.dist-info/metadata.json
sphinxcontrib_rextheme-0.1.2.dist-info/METADATA
sphinxcontrib_rextheme-0.1.2.dist-info/top_level.txt
sphinxcontrib_rextheme-0.1.2.dist-info/namespace_packages.txt
sphinxcontrib_rextheme-0.1.2.dist-info/entry_points.txt
sphinxcontrib_rextheme-0.1.2.dist-info/WHEEL
